{"temp":"25.3","hum":"50.0","lastUpdate":"16/03/2026 - 02:08:13","epochLastSeen":1773655693,"weekLabel":"16/03/2026","alertHigh":false,"alertLow":false,"tempMax":"25.8","tempMin":"25.3","humMax":"52.0","humMin":"50.0","hourHistory":[{"time":"00:00","temp":25.78312,"hum":50.79585},{"time":"01:00","temp":25.72044,"hum":50.00319},{"time":"02:00","temp":25.3,"hum":50}],"currentWeek":{"temp":[76.98065,0,0,0,0,0,0],"hum":[152.117,0,0,0,0,0,0],"count":[3,0,0,0,0,0,0],"offline":[false,false,false,false,false,false,false]},"weekHistory":[{"label":"09/03/2026","temp":[0,36.94361,174.7907,204.3772,258.1959,386.4782,546.9282],"hum":[0,117.7874,461.0936,618.0176,685.6092,965.6052,1019.647],"count":[0,2,8,10,13,19,25],"offline":[false,false,false,false,false,false,false]},{"label":"16/03/2026","temp":[360.2743,420.4955,343.2169,388.4055,150.56,441.7723,425.2461],"hum":[859.0113,961.8111,801.0373,767.3316,284.0814,725.9623,822.86],"count":[16,18,15,16,6,17,17],"offline":[false,false,false,false,false,false,false]}]}