{"temp":"19.4","hum":"53.0","lastUpdate":"06/03/2026 - 09:42:36","epochLastSeen":1772818956,"weekLabel":"02/03/2026","alertHigh":false,"alertLow":false,"tempMax":"30.8","tempMin":"19.4","humMax":"59.0","humMin":"42.0","hourHistory":[{"time":"04:00","temp":19.9444,"hum":57.69965},{"time":"05:00","temp":19.79989,"hum":56.85513},{"time":"06:00","temp":19.70498,"hum":54.17491},{"time":"07:00","temp":19.47001,"hum":53.79505},{"time":"08:00","temp":19.40005,"hum":53},{"time":"09:00","temp":19.46271,"hum":52.99254}],"currentWeek":{"temp":[0,36.94361,174.7907,204.3772,139.047,0,0],"hum":[0,117.7874,461.0936,618.0176,389.0909,0,0],"count":[0,2,8,10,7,0,0],"offline":[false,false,false,false,false,false,false]},"weekHistory":[]}