{"temp":"22.6","hum":"53.0","lastUpdate":"09/03/2026 - 01:45:20","epochLastSeen":1773049520,"weekLabel":"09/03/2026","alertHigh":false,"alertLow":false,"tempMax":"22.6","tempMin":"22.6","humMax":"53.0","humMin":"53.0","hourHistory":[{"time":"00:00","temp":22.60004,"hum":53},{"time":"01:00","temp":22.6,"hum":53}],"currentWeek":{"temp":[45.19968,0,0,0,0,0,0],"hum":[106.0097,0,0,0,0,0,0],"count":[2,0,0,0,0,0,0],"offline":[false,false,false,false,false,false,false]},"weekHistory":[{"label":"09/03/2026","temp":[0,36.94361,174.7907,204.3772,258.1959,386.4782,546.9282],"hum":[0,117.7874,461.0936,618.0176,685.6092,965.6052,1019.647],"count":[0,2,8,10,13,19,25],"offline":[false,false,false,false,false,false,false]}]}